blissdata_lima2/__init__.py
blissdata_lima2/stream.py
blissdata_lima2/tests/__init__.py
blissdata_lima2/tests/conftest.py
blissdata_lima2/tests/test_lima2_stream.py
blissdata_lima2-2.0.1.dist-info/licenses/LICENSE.md
blissdata_lima2-2.0.1.dist-info/METADATA
blissdata_lima2-2.0.1.dist-info/WHEEL
blissdata_lima2-2.0.1.dist-info/entry_points.txt
blissdata_lima2-2.0.1.dist-info/top_level.txt
blissdata_lima2-2.0.1.dist-info/RECORD
