Metadata-Version: 2.4
Name: blissdata-lima2
Version: 2.0.1
Summary: Lima2 plugin for blissdata
Maintainer: BCU (ESRF)
License-Expression: MIT
Project-URL: Repository, https://gitlab.esrf.fr/bliss/blissdata-lima2
Keywords: blissdata,lima2
Classifier: Intended Audience :: Science/Research
Classifier: Programming Language :: Python :: 3
Requires-Python: >=3.10
License-File: LICENSE.md
Requires-Dist: blissdata~=2.3
Requires-Dist: lima2-client~=4.0
Provides-Extra: dev
Requires-Dist: black; extra == "dev"
Requires-Dist: flake8; extra == "dev"
Requires-Dist: mypy; extra == "dev"
Requires-Dist: pytest; extra == "dev"
Requires-Dist: pytest-cov; extra == "dev"
Requires-Dist: pytest-redis; extra == "dev"
Dynamic: license-file
